Workbook

Sheet Financial_Data
C1: Monthly Financial Performance of Gym
A3: Month | B3: Rent | C3: Electricity | D3: Trainer Salary | E3: Total Cost | F3: Total Revenue | G3: Profit (Net Income) | H3: Profit Margin
A4: March | B4: 30000 | C4: 20000 | D4: 12000 | E4: =SUM(B4:D4) -> 62000 | F4: 80300 | G4: =F4-E4 -> 18300 | H4: =G4/F4 -> 0.22789539
A5: April | B5: 30000 | C5: 20000 | D5: 12000 | E5: =SUM(B5:D5) -> 62000 | F5: 112200 | G5: =F5-E5 -> 50200 | H5: =G5/F5 -> 0.44741533
A6: May | B6: 30000 | C6: 20000 | D6: 12000 | E6: =SUM(B6:D6) -> 62000 | F6: 66200 | G6: =F6-E6 -> 4200 | H6: =G6/F6 -> 0.063444109
A7: June | B7: 30000 | C7: 20000 | D7: 12000 | E7: =SUM(B7:D7) -> 62000 | F7: 89300 | G7: =F7-E7 -> 27300 | H7: =G7/F7 -> 0.30571109
A8: July | B8: 30000 | C8: 20000 | D8: 12000 | E8: =SUM(B8:D8) -> 62000 | F8: 96200 | G8: =F8-E8 -> 34200 | H8: =G8/F8 -> 0.35550936
A9: August | B9: 30000 | C9: 20000 | D9: 12000 | E9: =SUM(B9:D9) -> 62000 | F9: 69600 | G9: =F9-E9 -> 7600 | H9: =G9/F9 -> 0.1091954
A10: Total | B10: =SUM(B4:B9) -> 180000 | C10: =SUM(C4:C9) -> 120000 | D10: =SUM(D4:D9) -> 72000 | E10: =SUM(E4:E9) -> 372000 | F10: =SUM(F4:F9) -> 513800 | G10: =F10-E10 -> 141800 | H10: =G10/F10 -> 0.27598287

Sheet Charts_Dashboard
D2: Gym Business Performance Dashboard (Mar–Aug 2025)

Sheet Gym_data
E1: Gym Membership Payment Dataset (2025)
A3: Serial Number | B3: Payment_Date | C3: Member_id | D3: Member_Name | E3: Payment_Amount | F3: Plan_type | G3: Payment_Method | H3: Service_Type | I3: Month_Start_Date | J3: Expiry_Date | K3: Membership_Status | N3: ANALYSIS DATE | Q3: Membership_Duration_Days
A4: 88 | B4: 45717 | C4: =VLOOKUP(D4, Member_Master!A:B, 2, FALSE) -> M043 | D4: Deepjyoti Ghosh | E4: 1000 | F4: =IF(E4<=2200,"Monthly",IF(E4<=4500,"3 Months", IF(E4<=7000,"6 Months", "Yearly"))) -> Monthly | G4: Cash | H4: Normal | I4: 45717 | J4: =IF(F4="Monthly",B4+30,IF(F4="3 Months",B4+90,IF(F4="6 Months",B4+180,IF(F4="Yearly",B4+365,"Check Plan")))) -> 45747 | K4: =IF($N$4<=J4,"Active",IF($N$4-J4<=30,"At Risk","Churn Risk")) -> Churn Risk | N4: 45900 | Q4: Monthly | R4: 30
A5: 241 | B5: 45717 | C5: =VLOOKUP(D5, Member_Master!A:B, 2, FALSE) -> M117 | D5: Ripan Das | E5: 1000 | F5: =IF(E5<=2200,"Monthly",IF(E5<=4500,"3 Months", IF(E5<=7000,"6 Months", "Yearly"))) -> Monthly | G5: Google Pay | H5: Normal | I5: 45717 | J5: =IF(F5="Monthly",B5+30,IF(F5="3 Months",B5+90,IF(F5="6 Months",B5+180,IF(F5="Yearly",B5+365,"Check Plan")))) -> 45747 | K5: =IF($N$4<=J5,"Active",IF($N$4-J5<=30,"At Risk","Churn Risk")) -> Churn Risk | Q5: 3 Months | R5: 90
A6: 330 | B6: 45717 | C6: =VLOOKUP(D6, Member_Master!A:B, 2, FALSE) -> M176 | D6: Subhrojit Ghosh | E6: 1000 | F6: =IF(E6<=2200,"Monthly",IF(E6<=4500,"3 Months", IF(E6<=7000,"6 Months", "Yearly"))) -> Monthly | G6: Google Pay | H6: Normal | I6: 45717 | J6: =IF(F6="Monthly",B6+30,IF(F6="3 Months",B6+90,IF(F6="6 Months",B6+180,IF(F6="Yearly",B6+365,"Check Plan")))) -> 45747 | K6: =IF($N$4<=J6,"Active",IF($N$4-J6<=30,"At Risk","Churn Risk")) -> Churn Risk | Q6: 4 Months | R6: 180
A7: 134 | B7: 45719 | C7: =VLOOKUP(D7, Member_Master!A:B, 2, FALSE) -> M069 | D7: Kunal Debbarma | E7: 1000 | F7: =IF(E7<=2200,"Monthly",IF(E7<=4500,"3 Months", IF(E7<=7000,"6 Months", "Yearly"))) -> Monthly | G7: Cash | H7: Normal | I7: 45717 | J7: =IF(F7="Monthly",B7+30,IF(F7="3 Months",B7+90,IF(F7="6 Months",B7+180,IF(F7="Yearly",B7+365,"Check Plan")))) -> 45749 | K7: =IF($N$4<=J7,"Active",IF($N$4-J7<=30,"At Risk","Churn Risk")) -> Churn Risk | Q7: Yearly | R7: 365
A8: 62 | B8: 45720 | C8: =VLOOKUP(D8, Member_Master!A:B, 2, FALSE) -> M031 | D8: Basuraj Bhattacharjee | E8: 1000 | F8: =IF(E8<=2200,"Monthly",IF(E8<=4500,"3 Months", IF(E8<=7000,"6 Months", "Yearly"))) -> Monthly | G8: Google Pay | H8: Normal | I8: 45717 | J8: =IF(F8="Monthly",B8+30,IF(F8="3 Months",B8+90,IF(F8="6 Months",B8+180,IF(F8="Yearly",B8+365,"Check Plan")))) -> 45750 | K8: =IF($N$4<=J8,"Active",IF($N$4-J8<=30,"At Risk","Churn Risk")) -> Churn Risk
A9: 90 | B9: 45720 | C9: =VLOOKUP(D9, Member_Master!A:B, 2, FALSE) -> M044 | D9: Diksha Chaudhury | E9: 4800 | F9: =IF(E9<=2200,"Monthly",IF(E9<=4500,"3 Months", IF(E9<=7000,"6 Months", "Yearly"))) -> 6 Months | G9: Cash | H9: Normal | I9: 45717 | J9: =IF(F9="Monthly",B9+30,IF(F9="3 Months",B9+90,IF(F9="6 Months",B9+180,IF(F9="Yearly",B9+365,"Check Plan")))) -> 45900 | K9: =IF($N$4<=J9,"Active",IF($N$4-J9<=30,"At Risk","Churn Risk")) -> Active
A10: 170 | B10: 45720 | C10: =VLOOKUP(D10, Member_Master!A:B, 2, FALSE) -> M080 | D10: Minal Debbarma | E10: 1000 | F10: =IF(E10<=2200,"Monthly",IF(E10<=4500,"3 Months", IF(E10<=7000,"6 Months", "Yearly"))) -> Monthly | G10: Cash | H10: Normal | I10: 45717 | J10: =IF(F10="Monthly",B10+30,IF(F10="3 Months",B10+90,IF(F10="6 Months",B10+180,IF(F10="Yearly",B10+365,"Check Plan")))) -> 45750 | K10: =IF($N$4<=J10,"Active",IF($N$4-J10<=30,"At Risk","Churn Risk")) -> Churn Risk
A11: 202 | B11: 45720 | C11: =VLOOKUP(D11, Member_Master!A:B, 2, FALSE) -> M096 | D11: Prasenjit Sarkar | E11: 4800 | F11: =IF(E11<=2200,"Monthly",IF(E11<=4500,"3 Months", IF(E11<=7000,"6 Months", "Yearly"))) -> 6 Months | G11: Google Pay | H11: Normal | I11: 45717 | J11: =IF(F11="Monthly",B11+30,IF(F11="3 Months",B11+90,IF(F11="6 Months",B11+180,IF(F11="Yearly",B11+365,"Check Plan")))) -> 45900 | K11: =IF($N$4<=J11,"Active",IF($N$4-J11<=30,"At Risk","Churn Risk")) -> Active
A12: 221 | B12: 45720 | C12: =VLOOKUP(D12, Member_Master!A:B, 2, FALSE) -> M108 | D12: Rajat Saha | E12: 1000 | F12: =IF(E12<=2200,"Monthly",IF(E12<=4500,"3 Months", IF(E12<=7000,"6 Months", "Yearly"))) -> Monthly | G12: Google Pay | H12: Normal | I12: 45717 | J12: =IF(F12="Monthly",B12+30,IF(F12="3 Months",B12+90,IF(F12="6 Months",B12+180,IF(F12="Yearly",B12+365,"Check Plan")))) -> 45750 | K12: =IF($N$4<=J12,"Active",IF($N$4-J12<=30,"At Risk","Churn Risk")) -> Churn Risk
A13: 287 | B13: 45720 | C13: =VLOOKUP(D13, Member_Master!A:B, 2, FALSE) -> M145 | D13: Shaptadeep Debnath | E13: 1000 | F13: =IF(E13<=2200,"Monthly",IF(E13<=4500,"3 Months", IF(E13<=7000,"6 Months", "Yearly"))) -> Monthly | G13: Google Pay | H13: Normal | I13: 45717 | J13: =IF(F13="Monthly",B13+30,IF(F13="3 Months",B13+90,IF(F13="6 Months",B13+180,IF(F13="Yearly",B13+365,"Check Plan")))) -> 45750 | K13: =IF($N$4<=J13,"Active",IF($N$4-J13<=30,"At Risk","Churn Risk")) -> Churn Risk
A14: 122 | B14: 45721 | C14: =VLOOKUP(D14, Member_Master!A:B, 2, FALSE) -> M065 | D14: Kishor Das | E14: 1000 | F14: =IF(E14<=2200,"Monthly",IF(E14<=4500,"3 Months", IF(E14<=7000,"6 Months", "Yearly"))) -> Monthly | G14: Cash | H14: Normal | I14: 45717 | J14: =IF(F14="Monthly",B14+30,IF(F14="3 Months",B14+90,IF(F14="6 Months",B14+180,IF(F14="Yearly",B14+365,"Check Plan")))) -> 45751 | K14: =IF($N$4<=J14,"Active",IF($N$4-J14<=30,"At Risk","Churn Risk")) -> Churn Risk
A15: 183 | B15: 45721 | C15: =VLOOKUP(D15, Member_Master!A:B, 2, FALSE) -> M084 | D15: Nabajit Saha | E15: 1000 | F15: =IF(E15<=2200,"Monthly",IF(E15<=4500,"3 Months", IF(E15<=7000,"6 Months", "Yearly"))) -> Monthly | G15: Google Pay | H15: Normal | I15: 45717 | J15: =IF(F15="Monthly",B15+30,IF(F15="3 Months",B15+90,IF(F15="6 Months",B15+180,IF(F15="Yearly",B15+365,"Check Plan")))) -> 45751 | K15: =IF($N$4<=J15,"Active",IF($N$4-J15<=30,"At Risk","Churn Risk")) -> Churn Risk
A16: 197 | B16: 45721 | C16: =VLOOKUP(D16, Member_Master!A:B, 2, FALSE) -> M093 | D16: Pradip Das | E16: 1000 | F16: =IF(E16<=2200,"Monthly",IF(E16<=4500,"3 Months", IF(E16<=7000,"6 Months", "Yearly"))) -> Monthly | G16: Google Pay | H16: Normal | I16: 45717 | J16: =IF(F16="Monthly",B16+30,IF(F16="3 Months",B16+90,IF(F16="6 Months",B16+180,IF(F16="Yearly",B16+365,"Check Plan")))) -> 45751 | K16: =IF($N$4<=J16,"Active",IF($N$4-J16<=30,"At Risk","Churn Risk")) -> Churn Risk
A17: 199 | B17: 45721 | C17: =VLOOKUP(D17, Member_Master!A:B, 2, FALSE) -> M094 | D17: Pradip Majumder | E17: 2400 | F17: =IF(E17<=2200,"Monthly",IF(E17<=4500,"3 Months", IF(E17<=7000,"6 Months", "Yearly"))) -> 3 Months | G17: Google Pay | H17: Normal | I17: 45717 | J17: =IF(F17="Monthly",B17+30,IF(F17="3 Months",B17+90,IF(F17="6 Months",B17+180,IF(F17="Yearly",B17+365,"Check Plan")))) -> 45811 | K17: =IF($N$4<=J17,"Active",IF($N$4-J17<=30,"At Risk","Churn Risk")) -> Churn Risk
A18: 233 | B18: 45721 | C18: =VLOOKUP(D18, Member_Master!A:B, 2, FALSE) -> M112 | D18: Ranik Singha | E18: 1000 | F18: =IF(E18<=2200,"Monthly",IF(E18<=4500,"3 Months", IF(E18<=7000,"6 Months", "Yearly"))) -> Monthly | G18: Cash | H18: Normal | I18: 45717 | J18: =IF(F18="Monthly",B18+30,IF(F18="3 Months",B18+90,IF(F18="6 Months",B18+180,IF(F18="Yearly",B18+365,"Check Plan")))) -> 45751 | K18: =IF($N$4<=J18,"Active",IF($N$4-J18<=30,"At Risk","Churn Risk")) -> Churn Risk
A19: 371 | B19: 45721 | C19: =VLOOKUP(D19, Member_Master!A:B, 2, FALSE) -> M198 | D19: Tanmoy Dey | E19: 1000 | F19: =IF(E19<=2200,"Monthly",IF(E19<=4500,"3 Months", IF(E19<=7000,"6 Months", "Yearly"))) -> Monthly | G19: Google Pay | H19: Normal | I19: 45717 | J19: =IF(F19="Monthly",B19+30,IF(F19="3 Months",B19+90,IF(F19="6 Months",B19+180,IF(F19="Yearly",B19+365,"Check Plan")))) -> 45751 | K19: =IF($N$4<=J19,"Active",IF($N$4-J19<=30,"At Risk","Churn Risk")) -> Churn Risk
... A380: 322 | B380: 45888 | C380: =VLOOKUP(D380, Member_Master!A:B, 2, FALSE) -> M170 | D380: Subham Debnath | E380: 2400 | F380: =IF(E380<=2200,"Monthly",IF(E380<=4500,"3 Months", IF(E380<=7000,"6 Months", "Yearly"))) -> 3 Months | G380: Google Pay | H380: Normal | I380: 45870 | J380: =IF(F380="Monthly",B380+30,IF(F380="3 Months",B380+90,IF(F380="6 Months",B380+180,IF(F380="Yearly",B380+365,"Check Plan")))) -> 45978 | K380: =IF($N$4<=J380,"Active",IF($N$4-J380<=30,"At Risk","Churn Risk")) -> Active

Sheet Member_Summary
E1: Member Segmentation & RFM Analysis
A3: Member_Id | B3: Last Payment Date | C3: Expiry Date | D3: Membership_Status | E3: Recency | F3: Frequency | G3: Monetary | H3: R_Score | I3: F_Score | J3: M_Score | K3: RFM_Score | L3: Segment | M3: Plan_type | O3: ANALYSIS DATE
A4: M030 | B4: =_xlfn.MAXIFS(Gym_data!$B:$B,Gym_data!$C:$C,$A4) -> 45874 | C4: =IF(M4="Monthly",B4+30,IF(M4="3 Months",B4+90, IF(M4="6 Months",B4+180, IF(M4="Yearly",B4+365,"Check Plan")))) -> 45904 | D4: =IF($O$4<=C4,"Active",IF($O$4-C4<=30,"At Risk","Churn Risk")) -> Active | E4: =$O$4 - B4 -> 26 | F4: =COUNTIF(Gym_data!C:C, A4) -> 6 | G4: =SUMIF(Gym_data!C:C, A4, Gym_data!E:E) -> 6000 | H4: =IF(E4<=30,5,IF(E4<=60,4,IF(E4<=90,3,IF(E4<=120,2,1)))) -> 5 | I4: =IF(F4>=5,5, IF(F4>=4,4,IF(F4>=3,3,IF(F4>=2,2,1)))) -> 5 | J4: =IF(G4>=5000,5,IF(G4>=4000,4,IF(G4>=3000,3,IF(G4>=2000,2,1)))) -> 5 | K4: =H4&I4&J4 -> 555 | L4: =IF(AND(H4>=4,I4>=4,J4>=4),"Champion",IF(AND(H4>=3,I4>=3,J4>=3),"Loyal",IF(AND(H4>=4,I4<=2),"At Risk","Churn Risk"))) -> Champion | M4: {=_xlfn.XLOOKUP(1,(Gym_data!$C:$C=$A4)*(Gym_data!$B:$B=$B4),Gym_data!$F:$F)} -> Monthly | O4: 45900
A5: M032 | B5: =_xlfn.MAXIFS(Gym_data!$B:$B,Gym_data!$C:$C,$A5) -> 45875 | C5: =IF(M5="Monthly",B5+30,IF(M5="3 Months",B5+90, IF(M5="6 Months",B5+180, IF(M5="Yearly",B5+365,"Check Plan")))) -> 45905 | D5: =IF($O$4<=C5,"Active",IF($O$4-C5<=30,"At Risk","Churn Risk")) -> Active | E5: =$O$4 - B5 -> 25 | F5: =COUNTIF(Gym_data!C:C, A5) -> 6 | G5: =SUMIF(Gym_data!C:C, A5, Gym_data!E:E) -> 6000 | H5: =IF(E5<=30,5,IF(E5<=60,4,IF(E5<=90,3,IF(E5<=120,2,1)))) -> 5 | I5: =IF(F5>=5,5, IF(F5>=4,4,IF(F5>=3,3,IF(F5>=2,2,1)))) -> 5 | J5: =IF(G5>=5000,5,IF(G5>=4000,4,IF(G5>=3000,3,IF(G5>=2000,2,1)))) -> 5 | K5: =H5&I5&J5 -> 555 | L5: =IF(AND(H5>=4,I5>=4,J5>=4),"Champion",IF(AND(H5>=3,I5>=3,J5>=3),"Loyal",IF(AND(H5>=4,I5<=2),"At Risk","Churn Risk"))) -> Champion | M5: {=_xlfn.XLOOKUP(1,(Gym_data!$C:$C=$A5)*(Gym_data!$B:$B=$B5),Gym_data!$F:$F)} -> Monthly
A6: M065 | B6: =_xlfn.MAXIFS(Gym_data!$B:$B,Gym_data!$C:$C,$A6) -> 45875 | C6: =IF(M6="Monthly",B6+30,IF(M6="3 Months",B6+90, IF(M6="6 Months",B6+180, IF(M6="Yearly",B6+365,"Check Plan")))) -> 45905 | D6: =IF($O$4<=C6,"Active",IF($O$4-C6<=30,"At Risk","Churn Risk")) -> Active | E6: =$O$4 - B6 -> 25 | F6: =COUNTIF(Gym_data!C:C, A6) -> 6 | G6: =SUMIF(Gym_data!C:C, A6, Gym_data!E:E) -> 6000 | H6: =IF(E6<=30,5,IF(E6<=60,4,IF(E6<=90,3,IF(E6<=120,2,1)))) -> 5 | I6: =IF(F6>=5,5, IF(F6>=4,4,IF(F6>=3,3,IF(F6>=2,2,1)))) -> 5 | J6: =IF(G6>=5000,5,IF(G6>=4000,4,IF(G6>=3000,3,IF(G6>=2000,2,1)))) -> 5 | K6: =H6&I6&J6 -> 555 | L6: =IF(AND(H6>=4,I6>=4,J6>=4),"Champion",IF(AND(H6>=3,I6>=3,J6>=3),"Loyal",IF(AND(H6>=4,I6<=2),"At Risk","Churn Risk"))) -> Champion | M6: {=_xlfn.XLOOKUP(1,(Gym_data!$C:$C=$A6)*(Gym_data!$B:$B=$B6),Gym_data!$F:$F)} -> Monthly
A7: M069 | B7: =_xlfn.MAXIFS(Gym_data!$B:$B,Gym_data!$C:$C,$A7) -> 45875 | C7: =IF(M7="Monthly",B7+30,IF(M7="3 Months",B7+90, IF(M7="6 Months",B7+180, IF(M7="Yearly",B7+365,"Check Plan")))) -> 45905 | D7: =IF($O$4<=C7,"Active",IF($O$4-C7<=30,"At Risk","Churn Risk")) -> Active | E7: =$O$4 - B7 -> 25 | F7: =COUNTIF(Gym_data!C:C, A7) -> 6 | G7: =SUMIF(Gym_data!C:C, A7, Gym_data!E:E) -> 6000 | H7: =IF(E7<=30,5,IF(E7<=60,4,IF(E7<=90,3,IF(E7<=120,2,1)))) -> 5 | I7: =IF(F7>=5,5, IF(F7>=4,4,IF(F7>=3,3,IF(F7>=2,2,1)))) -> 5 | J7: =IF(G7>=5000,5,IF(G7>=4000,4,IF(G7>=3000,3,IF(G7>=2000,2,1)))) -> 5 | K7: =H7&I7&J7 -> 555 | L7: =IF(AND(H7>=4,I7>=4,J7>=4),"Champion",IF(AND(H7>=3,I7>=3,J7>=3),"Loyal",IF(AND(H7>=4,I7<=2),"At Risk","Churn Risk"))) -> Champion | M7: {=_xlfn.XLOOKUP(1,(Gym_data!$C:$C=$A7)*(Gym_data!$B:$B=$B7),Gym_data!$F:$F)} -> Monthly
A8: M070 | B8: =_xlfn.MAXIFS(Gym_data!$B:$B,Gym_data!$C:$C,$A8) -> 45877 | C8: =IF(M8="Monthly",B8+30,IF(M8="3 Months",B8+90, IF(M8="6 Months",B8+180, IF(M8="Yearly",B8+365,"Check Plan")))) -> 45967 | D8: =IF($O$4<=C8,"Active",IF($O$4-C8<=30,"At Risk","Churn Risk")) -> Active | E8: =$O$4 - B8 -> 23 | F8: =COUNTIF(Gym_data!C:C, A8) -> 5 | G8: =SUMIF(Gym_data!C:C, A8, Gym_data!E:E) -> 10000 | H8: =IF(E8<=30,5,IF(E8<=60,4,IF(E8<=90,3,IF(E8<=120,2,1)))) -> 5 | I8: =IF(F8>=5,5, IF(F8>=4,4,IF(F8>=3,3,IF(F8>=2,2,1)))) -> 5 | J8: =IF(G8>=5000,5,IF(G8>=4000,4,IF(G8>=3000,3,IF(G8>=2000,2,1)))) -> 5 | K8: =H8&I8&J8 -> 555 | L8: =IF(AND(H8>=4,I8>=4,J8>=4),"Champion",IF(AND(H8>=3,I8>=3,J8>=3),"Loyal",IF(AND(H8>=4,I8<=2),"At Risk","Churn Risk"))) -> Champion | M8: {=_xlfn.XLOOKUP(1,(Gym_data!$C:$C=$A8)*(Gym_data!$B:$B=$B8),Gym_data!$F:$F)} -> 3 Months
A9: M071 | B9: =_xlfn.MAXIFS(Gym_data!$B:$B,Gym_data!$C:$C,$A9) -> 45881 | C9: =IF(M9="Monthly",B9+30,IF(M9="3 Months",B9+90, IF(M9="6 Months",B9+180, IF(M9="Yearly",B9+365,"Check Plan")))) -> 45911 | D9: =IF($O$4<=C9,"Active",IF($O$4-C9<=30,"At Risk","Churn Risk")) -> Active | E9: =$O$4 - B9 -> 19 | F9: =COUNTIF(Gym_data!C:C, A9) -> 5 | G9: =SUMIF(Gym_data!C:C, A9, Gym_data!E:E) -> 6000 | H9: =IF(E9<=30,5,IF(E9<=60,4,IF(E9<=90,3,IF(E9<=120,2,1)))) -> 5 | I9: =IF(F9>=5,5, IF(F9>=4,4,IF(F9>=3,3,IF(F9>=2,2,1)))) -> 5 | J9: =IF(G9>=5000,5,IF(G9>=4000,4,IF(G9>=3000,3,IF(G9>=2000,2,1)))) -> 5 | K9: =H9&I9&J9 -> 555 | L9: =IF(AND(H9>=4,I9>=4,J9>=4),"Champion",IF(AND(H9>=3,I9>=3,J9>=3),"Loyal",IF(AND(H9>=4,I9<=2),"At Risk","Churn Risk"))) -> Champion | M9: {=_xlfn.XLOOKUP(1,(Gym_data!$C:$C=$A9)*(Gym_data!$B:$B=$B9),Gym_data!$F:$F)} -> Monthly
A10: M076 | B10: =_xlfn.MAXIFS(Gym_data!$B:$B,Gym_data!$C:$C,$A10) -> 45881 | C10: =IF(M10="Monthly",B10+30,IF(M10="3 Months",B10+90, IF(M10="6 Months",B10+180, IF(M10="Yearly",B10+365,"Check Plan")))) -> 45971 | D10: =IF($O$4<=C10,"Active",IF($O$4-C10<=30,"At Risk","Churn Risk")) -> Active | E10: =$O$4 - B10 -> 19 | F10: =COUNTIF(Gym_data!C:C, A10) -> 5 | G10: =SUMIF(Gym_data!C:C, A10, Gym_data!E:E) -> 15000 | H10: =IF(E10<=30,5,IF(E10<=60,4,IF(E10<=90,3,IF(E10<=120,2,1)))) -> 5 | I10: =IF(F10>=5,5, IF(F10>=4,4,IF(F10>=3,3,IF(F10>=2,2,1)))) -> 5 | J10: =IF(G10>=5000,5,IF(G10>=4000,4,IF(G10>=3000,3,IF(G10>=2000,2,1)))) -> 5 | K10: =H10&I10&J10 -> 555 | L10: =IF(AND(H10>=4,I10>=4,J10>=4),"Champion",IF(AND(H10>=3,I10>=3,J10>=3),"Loyal",IF(AND(H10>=4,I10<=2),"At Risk","Churn Risk"))) -> Champion | M10: {=_xlfn.XLOOKUP(1,(Gym_data!$C:$C=$A10)*(Gym_data!$B:$B=$B10),Gym_data!$F:$F)} -> 3 Months
A11: M080 | B11: =_xlfn.MAXIFS(Gym_data!$B:$B,Gym_data!$C:$C,$A11) -> 45874 | C11: =IF(M11="Monthly",B11+30,IF(M11="3 Months",B11+90, IF(M11="6 Months",B11+180, IF(M11="Yearly",B11+365,"Check Plan")))) -> 45904 | D11: =IF($O$4<=C11,"Active",IF($O$4-C11<=30,"At Risk","Churn Risk")) -> Active | E11: =$O$4 - B11 -> 26 | F11: =COUNTIF(Gym_data!C:C, A11) -> 7 | G11: =SUMIF(Gym_data!C:C, A11, Gym_data!E:E) -> 7000 | H11: =IF(E11<=30,5,IF(E11<=60,4,IF(E11<=90,3,IF(E11<=120,2,1)))) -> 5 | I11: =IF(F11>=5,5, IF(F11>=4,4,IF(F11>=3,3,IF(F11>=2,2,1)))) -> 5 | J11: =IF(G11>=5000,5,IF(G11>=4000,4,IF(G11>=3000,3,IF(G11>=2000,2,1)))) -> 5 | K11: =H11&I11&J11 -> 555 | L11: =IF(AND(H11>=4,I11>=4,J11>=4),"Champion",IF(AND(H11>=3,I11>=3,J11>=3),"Loyal",IF(AND(H11>=4,I11<=2),"At Risk","Churn Risk"))) -> Champion | M11: {=_xlfn.XLOOKUP(1,(Gym_data!$C:$C=$A11)*(Gym_data!$B:$B=$B11),Gym_data!$F:$F)} -> Monthly
A12: M081 | B12: =_xlfn.MAXIFS(Gym_data!$B:$B,Gym_data!$C:$C,$A12) -> 45875 | C12: =IF(M12="Monthly",B12+30,IF(M12="3 Months",B12+90, IF(M12="6 Months",B12+180, IF(M12="Yearly",B12+365,"Check Plan")))) -> 45905 | D12: =IF($O$4<=C12,"Active",IF($O$4-C12<=30,"At Risk","Churn Risk")) -> Active | E12: =$O$4 - B12 -> 25 | F12: =COUNTIF(Gym_data!C:C, A12) -> 5 | G12: =SUMIF(Gym_data!C:C, A12, Gym_data!E:E) -> 9800 | H12: =IF(E12<=30,5,IF(E12<=60,4,IF(E12<=90,3,IF(E12<=120,2,1)))) -> 5 | I12: =IF(F12>=5,5, IF(F12>=4,4,IF(F12>=3,3,IF(F12>=2,2,1)))) -> 5 | J12: =IF(G12>=5000,5,IF(G12>=4000,4,IF(G12>=3000,3,IF(G12>=2000,2,1)))) -> 5 | K12: =H12&I12&J12 -> 555 | L12: =IF(AND(H12>=4,I12>=4,J12>=4),"Champion",IF(AND(H12>=3,I12>=3,J12>=3),"Loyal",IF(AND(H12>=4,I12<=2),"At Risk","Churn Risk"))) -> Champion | M12: {=_xlfn.XLOOKUP(1,(Gym_data!$C:$C=$A12)*(Gym_data!$B:$B=$B12),Gym_data!$F:$F)} -> Monthly
A13: M117 | B13: =_xlfn.MAXIFS(Gym_data!$B:$B,Gym_data!$C:$C,$A13) -> 45887 | C13: =IF(M13="Monthly",B13+30,IF(M13="3 Months",B13+90, IF(M13="6 Months",B13+180, IF(M13="Yearly",B13+365,"Check Plan")))) -> 45917 | D13: =IF($O$4<=C13,"Active",IF($O$4-C13<=30,"At Risk","Churn Risk")) -> Active | E13: =$O$4 - B13 -> 13 | F13: =COUNTIF(Gym_data!C:C, A13) -> 6 | G13: =SUMIF(Gym_data!C:C, A13, Gym_data!E:E) -> 6000 | H13: =IF(E13<=30,5,IF(E13<=60,4,IF(E13<=90,3,IF(E13<=120,2,1)))) -> 5 | I13: =IF(F13>=5,5, IF(F13>=4,4,IF(F13>=3,3,IF(F13>=2,2,1)))) -> 5 | J13: =IF(G13>=5000,5,IF(G13>=4000,4,IF(G13>=3000,3,IF(G13>=2000,2,1)))) -> 5 | K13: =H13&I13&J13 -> 555 | L13: =IF(AND(H13>=4,I13>=4,J13>=4),"Champion",IF(AND(H13>=3,I13>=3,J13>=3),"Loyal",IF(AND(H13>=4,I13<=2),"At Risk","Churn Risk"))) -> Champion | M13: {=_xlfn.XLOOKUP(1,(Gym_data!$C:$C=$A13)*(Gym_data!$B:$B=$B13),Gym_data!$F:$F)} -> Monthly
A14: M197 | B14: =_xlfn.MAXIFS(Gym_data!$B:$B,Gym_data!$C:$C,$A14) -> 45876 | C14: =IF(M14="Monthly",B14+30,IF(M14="3 Months",B14+90, IF(M14="6 Months",B14+180, IF(M14="Yearly",B14+365,"Check Plan")))) -> 45906 | D14: =IF($O$4<=C14,"Active",IF($O$4-C14<=30,"At Risk","Churn Risk")) -> Active | E14: =$O$4 - B14 -> 24 | F14: =COUNTIF(Gym_data!C:C, A14) -> 5 | G14: =SUMIF(Gym_data!C:C, A14, Gym_data!E:E) -> 5000 | H14: =IF(E14<=30,5,IF(E14<=60,4,IF(E14<=90,3,IF(E14<=120,2,1)))) -> 5 | I14: =IF(F14>=5,5, IF(F14>=4,4,IF(F14>=3,3,IF(F14>=2,2,1)))) -> 5 | J14: =IF(G14>=5000,5,IF(G14>=4000,4,IF(G14>=3000,3,IF(G14>=2000,2,1)))) -> 5 | K14: =H14&I14&J14 -> 555 | L14: =IF(AND(H14>=4,I14>=4,J14>=4),"Champion",IF(AND(H14>=3,I14>=3,J14>=3),"Loyal",IF(AND(H14>=4,I14<=2),"At Risk","Churn Risk"))) -> Champion | M14: {=_xlfn.XLOOKUP(1,(Gym_data!$C:$C=$A14)*(Gym_data!$B:$B=$B14),Gym_data!$F:$F)} -> Monthly
A15: M177 | B15: =_xlfn.MAXIFS(Gym_data!$B:$B,Gym_data!$C:$C,$A15) -> 45887 | C15: =IF(M15="Monthly",B15+30,IF(M15="3 Months",B15+90, IF(M15="6 Months",B15+180, IF(M15="Yearly",B15+365,"Check Plan")))) -> 45917 | D15: =IF($O$4<=C15,"Active",IF($O$4-C15<=30,"At Risk","Churn Risk")) -> Active | E15: =$O$4 - B15 -> 13 | F15: =COUNTIF(Gym_data!C:C, A15) -> 5 | G15: =SUMIF(Gym_data!C:C, A15, Gym_data!E:E) -> 4500 | H15: =IF(E15<=30,5,IF(E15<=60,4,IF(E15<=90,3,IF(E15<=120,2,1)))) -> 5 | I15: =IF(F15>=5,5, IF(F15>=4,4,IF(F15>=3,3,IF(F15>=2,2,1)))) -> 5 | J15: =IF(G15>=5000,5,IF(G15>=4000,4,IF(G15>=3000,3,IF(G15>=2000,2,1)))) -> 4 | K15: =H15&I15&J15 -> 554 | L15: =IF(AND(H15>=4,I15>=4,J15>=4),"Champion",IF(AND(H15>=3,I15>=3,J15>=3),"Loyal",IF(AND(H15>=4,I15<=2),"At Risk","Churn Risk"))) -> Champion | M15: {=_xlfn.XLOOKUP(1,(Gym_data!$C:$C=$A15)*(Gym_data!$B:$B=$B15),Gym_data!$F:$F)} -> Monthly
A16: M008 | B16: =_xlfn.MAXIFS(Gym_data!$B:$B,Gym_data!$C:$C,$A16) -> 45887 | C16: =IF(M16="Monthly",B16+30,IF(M16="3 Months",B16+90, IF(M16="6 Months",B16+180, IF(M16="Yearly",B16+365,"Check Plan")))) -> 45917 | D16: =IF($O$4<=C16,"Active",IF($O$4-C16<=30,"At Risk","Churn Risk")) -> Active | E16: =$O$4 - B16 -> 13 | F16: =COUNTIF(Gym_data!C:C, A16) -> 4 | G16: =SUMIF(Gym_data!C:C, A16, Gym_data!E:E) -> 4000 | H16: =IF(E16<=30,5,IF(E16<=60,4,IF(E16<=90,3,IF(E16<=120,2,1)))) -> 5 | I16: =IF(F16>=5,5, IF(F16>=4,4,IF(F16>=3,3,IF(F16>=2,2,1)))) -> 4 | J16: =IF(G16>=5000,5,IF(G16>=4000,4,IF(G16>=3000,3,IF(G16>=2000,2,1)))) -> 4 | K16: =H16&I16&J16 -> 544 | L16: =IF(AND(H16>=4,I16>=4,J16>=4),"Champion",IF(AND(H16>=3,I16>=3,J16>=3),"Loyal",IF(AND(H16>=4,I16<=2),"At Risk","Churn Risk"))) -> Champion | M16: {=_xlfn.XLOOKUP(1,(Gym_data!$C:$C=$A16)*(Gym_data!$B:$B=$B16),Gym_data!$F:$F)} -> Monthly
... A204: M199 | B204: =_xlfn.MAXIFS(Gym_data!$B:$B,Gym_data!$C:$C,$A204) -> 45779 | C204: =IF(M204="Monthly",B204+30,IF(M204="3 Months",B204+90, IF(M204="6 Months",B204+180, IF(M204="Yearly",B204+365,"Check Plan")))) -> 45809 | D204: =IF($O$4<=C204,"Active",IF($O$4-C204<=30,"At Risk","Churn Risk")) -> Churn Risk | E204: =$O$4 - B204 -> 121 | F204: =COUNTIF(Gym_data!C:C, A204) -> 1 | G204: =SUMIF(Gym_data!C:C, A204, Gym_data!E:E) -> 1000 | H204: =IF(E204<=30,5,IF(E204<=60,4,IF(E204<=90,3,IF(E204<=120,2,1)))) -> 1 | I204: =IF(F204>=5,5, IF(F204>=4,4,IF(F204>=3,3,IF(F204>=2,2,1)))) -> 1 | J204: =IF(G204>=5000,5,IF(G204>=4000,4,IF(G204>=3000,3,IF(G204>=2000,2,1)))) -> 1 | K204: =H204&I204&J204 -> 111 | L204: =IF(AND(H204>=4,I204>=4,J204>=4),"Champion",IF(AND(H204>=3,I204>=3,J204>=3),"Loyal",IF(AND(H204>=4,I204<=2),"At Risk","Churn Risk"))) -> Churn Risk | M204: {=_xlfn.XLOOKUP(1,(Gym_data!$C:$C=$A204)*(Gym_data!$B:$B=$B204),Gym_data!$F:$F)} -> Monthly

Sheet Member_Master
A1: Member Master Data
A3: Member_Name | B3: Member_Id
A4: Aayush Paul | B4: M001
A5: Abdul Azir | B5: M002
A6: Abhijit Karmakar | B6: M003
A7: Abhijit Saha Bhowmik | B7: M004
A8: Aditya Kumar Sinha | B8: M005
A9: Aishwarika Debnath | B9: M006
A10: Akash Nandi | B10: M007
A11: Aman Paul | B11: M008
A12: Ambarish Mahalambish | B12: M009
A13: Anal Sharma | B13: M010
A14: Anamika Rupini | B14: M011
... A204: Udaysagar Roy | B204: M201

Sheet Pivot_Data
Q2: Pivot Tables for Analysis (Source for Dashboard Charts)
P4: Months | Q4: Revenue | S4: Months | T4: Profit | V4: Row Labels | W4: Number of members
P5: Mar | Q5: 80300 | S5: March | T5: 18300 | V5: Active | W5: 81
P6: Apr | Q6: 112200 | S6: April | T6: 50200 | V6: At Risk | W6: 59
P7: May | Q7: 66200 | S7: May | T7: 4200 | V7: Churn Risk | W7: 237
P8: Jun | Q8: 89300 | S8: June | T8: 27300 | V8: Grand Total | W8: 377
P9: Jul | Q9: 96200 | S9: July | T9: 34200
P10: Aug | Q10: 69600 | S10: August | T10: 7600 | V10: Member Status | W10: Revenue
P11: Grand Total | Q11: 513800 | S11: Grand Total | T11: 141800 | V11: At Risk | W11: 109100
V12: Champion | W12: 146700
V13: Churn Risk | W13: 207000
P14: Member Status | Q14: Number of Members | S14: Months | T14: Number of Active Members | V14: Loyal | W14: 51000
P15: At Risk | Q15: 62 | S15: Mar | T15: 56 | V15: Grand Total | W15: 513800
P16: Champion | Q16: 26 | S16: Apr | T16: 73
P17: Churn Risk | Q17: 100 | S17: May | T17: 55 | V17: Service Type | W17: Revenue
P18: Loyal | Q18: 13 | S18: Jun | T18: 64 | V18: Normal | W18: 438300
P19: Grand Total | Q19: 201 | S19: Jul | T19: 74 | V19: Personal Training | W19: 75500
S20: Aug | T20: 55 | V20: Grand Total | W20: 513800
S21: Grand Total | T21: 377
